content_bbcode
